{
  "generated_utc": "2026-05-20T03:48:38Z",
  "dataset_id": "swrz-ak2i",
  "row_count": 111,
  "rows": [
    {"action_taken_cid":"WARNING","age_range_cid":"46+","data_source":"AXON RMS","field_subject_cid":"PEDESTRIAN","instance_id":"a365a671-b2ed-4132-ab58-c23d13601b89","interview_date":"2026-12-10T17:15:00.000","is_juvenile":false,"latitude_x":"39.116","location_type":"STREET_ADDRESS","location_x":"14XX Race St Cincinnati, OH","longitude_x":"-84.5175","officer_assignment":"PV","race":"WHITE","sex":"MALE","sna_neighborhood":"Over-the-Rhine"},
    {"action_taken_cid":"NONE","age_range_cid":"0-17","data_source":"AXON RMS","district":"CP4","event_number":"CPD260429000060","field_subject_cid":"PEDESTRIAN","instance_id":"c8c168fc-cbd3-4e6f-a7cc-d9fbb9770d03","interview_date":"2026-04-29T06:38:00.000","is_juvenile":true,"latitude_x":"39.1935","location_type":"STREET_ADDRESS","location_x":"53XX Winneste Ave Cincinnati, OH","longitude_x":"-84.5126","priority":"124","race":"BLACK_OR_AFRICAN_AMERICAN","sex":"MALE","sna_neighborhood":"Winton Hills"},
    {"action_taken_cid":"NONE","age_range_cid":"0-17","data_source":"AXON RMS","district":"CP4","event_number":"CPD260429000060","field_subject_cid":"PEDESTRIAN","instance_id":"c8c168fc-cbd3-4e6f-a7cc-d9fbb9770d03","interview_date":"2026-04-29T06:38:00.000","is_juvenile":true,"latitude_x":"39.187","location_type":"STREET_ADDRESS","location_x":"53XX Winneste Ave Cincinnati, OH","longitude_x":"-84.5139","priority":"124","race":"UNKNOWN","sex":"MALE","sna_neighborhood":"Winton Hills"},
    {"action_taken_cid":"NONE","age_range_cid":"0-17","data_source":"AXON RMS","district":"CP4","event_number":"CPD260429000060","field_subject_cid":"PEDESTRIAN","instance_id":"c8c168fc-cbd3-4e6f-a7cc-d9fbb9770d03","interview_date":"2026-04-29T06:38:00.000","is_juvenile":true,"latitude_x":"39.185","location_type":"STREET_ADDRESS","location_x":"53XX Winneste Ave Cincinnati, OH","longitude_x":"-84.5129","priority":"124","race":"BLACK_OR_AFRICAN_AMERICAN","sex":"MALE","sna_neighborhood":"Winton Hills"},
    {"action_taken_cid":"CITATION_TRAFFIC","age_range_cid":"0-17","data_source":"AXON RMS","district":"CBS","event_number":"CPD260428001253","field_subject_cid":"PEDESTRIAN","instance_id":"bacdbc4a-b640-4fd0-8dea-ffef723be744","interview_date":"2026-04-28T20:44:00.000","is_juvenile":true,"latitude_x":"39.1002","location_type":"STREET_ADDRESS","location_x":"3XX Main St Cincinnati, OH","longitude_x":"-84.509","officer_assignment":"CB_B","priority":"125","race":"BLACK_OR_AFRICAN_AMERICAN","sex":"MALE","sna_neighborhood":"Downtown"},
    {"action_taken_cid":"CITATION_TRAFFIC","age_range_cid":"0-17","data_source":"AXON RMS","district":"CBS","event_number":"CPD260428001253","field_subject_cid":"PEDESTRIAN","instance_id":"bacdbc4a-b640-4fd0-8dea-ffef723be744","interview_date":"2026-04-28T20:44:00.000","is_juvenile":true,"latitude_x":"39.1028","location_type":"STREET_ADDRESS","location_x":"3XX Main St Cincinnati, OH","longitude_x":"-84.5088","officer_assignment":"CB_B","priority":"125","race":"BLACK_OR_AFRICAN_AMERICAN","sex":"MALE","sna_neighborhood":"Downtown"},
    {"age_range_cid":"18-25","data_source":"AXON RMS","district":"CP4","event_number":"CPD260428001067","field_subject_cid":"PEDESTRIAN","instance_id":"fe10466b-42fd-4f8d-abdd-b4675e0463aa","interview_date":"2026-04-28T19:32:00.000","is_juvenile":false,"latitude_x":"39.1758","location_type":"STREET_ADDRESS","location_x":"46XX Kings Run Dr Cincinnati, OH","longitude_x":"-84.5093","officer_assignment":"D_4_S","priority":"125","race":"BLACK","sex":"MALE","sna_neighborhood":"Spring Grove Village"},
    {"action_taken_cid":"WARNING","age_range_cid":"46+","data_source":"AXON RMS","district":"CP1","event_number":"CPD260428001061","field_subject_cid":"PEDESTRIAN","instance_id":"fab8e8c1-9c4c-4f08-a974-ca835bdb1699","interview_date":"2026-04-28T19:28:00.000","is_juvenile":false,"location_type":"CROSS_STREET","location_x":"Green St and Republic St","officer_assignment":"D_1_S","priority":"122","race":"BLACK_OR_AFRICAN_AMERICAN","sex":"MALE"},
    {"action_taken_cid":"CITATION_MISD","age_range_cid":"18-25","data_source":"AXON RMS","district":"CP4","event_number":"CPD260428000983","field_subject_cid":"PEDESTRIAN","instance_id":"d238d66e-1ce0-4ab7-a8f8-3bfdeffec7d3","interview_date":"2026-04-28T19:10:00.000","is_juvenile":false,"latitude_x":"39.1954","location_type":"STREET_ADDRESS","location_x":"54XX Hebron Ct Cincinnati, OH","longitude_x":"-84.5168","officer_assignment":"D_4_S","priority":"125","race":"BLACK_OR_AFRICAN_AMERICAN","sex":"MALE","sna_neighborhood":"Winton Hills"},
    {"action_taken_cid":"WARNING","age_range_cid":"46+","data_source":"AXON RMS","district":"CP2","event_number":"CPD260428000426","field_subject_cid":"PEDESTRIAN","instance_id":"0c805797-5aff-4766-a934-dea7bff9a371","interview_date":"2026-04-28T14:02:00.000","is_juvenile":false,"latitude_x":"39.1328","location_type":"STREET_ADDRESS","location_x":"29XX Gilbert Ave Cincinnati, OH","longitude_x":"-84.4889","officer_assignment":"D_2_N","priority":"122","race":"BLACK_OR_AFRICAN_AMERICAN","sex":"MALE","sna_neighborhood":"Walnut Hills"},
    {"action_taken_cid":"ARREST_FELONY","age_range_cid":"36-45","data_source":"AXON RMS","district":"CP1","event_number":"CPD260420001957","field_subject_cid":"PEDESTRIAN","instance_id":"7ac70ef0-230a-423e-b43d-6dfe49b1e3f4","interview_date":"2026-04-28T13:27:00.000","is_juvenile":false,"latitude_x":"39.123","location_type":"STREET_ADDRESS","location_x":"1XX W Elder St Cincinnati, OH","longitude_x":"-84.5187","officer_assignment":"PV","priority":"125","race":"BLACK_OR_AFRICAN_AMERICAN","sex":"MALE","sna_neighborhood":"Over-the-Rhine"},
    {"action_taken_cid":"WARNING","age_range_cid":"36-45","data_source":"AXON RMS","district":"CP4","event_number":"CPD260428000194","field_subject_cid":"PEDESTRIAN","instance_id":"825e7a4a-8c80-42eb-bbbb-e37532bbff15","interview_date":"2026-04-28T10:57:00.000","is_juvenile":false,"latitude_x":"39.1287","location_type":"STREET_ADDRESS","location_x":"2XX Stetson St Cincinnati, OH","longitude_x":"-84.5027","officer_assignment":"D_4_F","priority":"124","race":"WHITE","sex":"MALE","sna_neighborhood":"Corryville"},
    {"action_taken_cid":"WARNING","age_range_cid":"36-45","data_source":"AXON RMS","district":"CP3","event_number":"CPD260427001672","field_subject_cid":"PEDESTRIAN","instance_id":"03c07bbd-2fdc-47c6-a996-5c0e4c1e5b37","interview_date":"2026-04-28T01:32:00.000","is_juvenile":false,"latitude_x":"39.1359","location_type":"STREET_ADDRESS","location_x":"13XX Hopple St Cincinnati, OH","longitude_x":"-84.5382","priority":"124","race":"WHITE","sex":"MALE","sna_neighborhood":"Camp Washington"},
    {"action_taken_cid":"WARNING","age_range_cid":"18-25","data_source":"AXON RMS","district":"CP1","event_number":"CPD260427001462","field_subject_cid":"PEDESTRIAN","instance_id":"990a5439-07fc-4029-b64a-6d719db0463e","interview_date":"2026-04-27T22:32:00.000","is_juvenile":false,"location_type":"CROSS_STREET","location_x":"Liberty St and Race St","officer_assignment":"D_1_S","priority":"122","race":"BLACK_OR_AFRICAN_AMERICAN","sex":"MALE"},
    {"action_taken_cid":"CITATION_CAPIAS_WAR","age_range_cid":"18-25","data_source":"AXON RMS","district":"CP1","event_number":"CPD260427001462","field_subject_cid":"PEDESTRIAN","instance_id":"990a5439-07fc-4029-b64a-6d719db0463e","interview_date":"2026-04-27T22:32:00.000","is_juvenile":false,"location_type":"CROSS_STREET","location_x":"Liberty St and Race St","officer_assignment":"D_1_S","priority":"122","race":"BLACK_OR_AFRICAN_AMERICAN","sex":"MALE"},
    {"action_taken_cid":"WARNING","age_range_cid":"18-25","data_source":"AXON RMS","district":"CP1","event_number":"CPD260427001462","field_subject_cid":"PEDESTRIAN","instance_id":"990a5439-07fc-4029-b64a-6d719db0463e","interview_date":"2026-04-27T22:32:00.000","is_juvenile":false,"location_type":"CROSS_STREET","location_x":"Liberty St and Race St","officer_assignment":"D_1_S","priority":"122","race":"BLACK_OR_AFRICAN_AMERICAN","sex":"MALE"},
    {"action_taken_cid":"OTHER","age_range_cid":"0-17","data_source":"AXON RMS","district":"CP2","event_number":"CPD260427001176","field_subject_cid":"PEDESTRIAN","instance_id":"b7054332-ff8a-4279-9447-4a8c5f07f755","interview_date":"2026-04-27T20:06:00.000","is_juvenile":true,"latitude_x":"39.1658","location_type":"STREET_ADDRESS","location_x":"33XX Ibsen Ave Cincinnati, OH","longitude_x":"-84.4226","officer_assignment":"D_2_S","priority":"123","race":"BLACK_OR_AFRICAN_AMERICAN","sex":"FEMALE","sna_neighborhood":"Oakley"},
    {"action_taken_cid":"CITATION_CAPIAS_WAR_ARREST_FELONY","age_range_cid":"36-45","data_source":"AXON RMS","district":"CP1","event_number":"CPD260427001058","field_subject_cid":"PEDESTRIAN","instance_id":"c8e73bd9-01b0-42f6-8938-448e561c79c6","interview_date":"2026-04-27T19:42:00.000","is_juvenile":false,"latitude_x":"39.1091","location_type":"STREET_ADDRESS","location_x":"XX Green St Cincinnati, OH","longitude_x":"-84.5178","officer_assignment":"D_1_VCS","priority":"125","race":"BLACK_OR_AFRICAN_AMERICAN","sex":"MALE","sna_neighborhood":"Over-the-Rhine"},
    {"action_taken_cid":"WARNING","age_range_cid":"46+","data_source":"AXON RMS","district":"CP1","event_number":"CPD260427000944","field_subject_cid":"PEDESTRIAN","instance_id":"7bc64f0b-b400-4733-a1ef-1dc5f33c628d","interview_date":"2026-04-27T18:16:00.000","is_juvenile":false,"latitude_x":"39.114","location_type":"STREET_ADDRESS","location_x":"15XX Republic St Cincinnati, OH","longitude_x":"-84.5178","officer_assignment":"D_1_S","priority":"122","race":"BLACK_OR_AFRICAN_AMERICAN","sex":"MALE","sna_neighborhood":"Over-the-Rhine"},
    {"action_taken_cid":"NONE","age_range_cid":"46+","data_source":"AXON RMS","district":"CP3","event_number":"CPD260427000095","field_subject_cid":"PEDESTRIAN","instance_id":"131f81ff-3d40-4a30-a8ba-99632c4c2718","interview_date":"2026-04-27T06:12:00.000","is_juvenile":false,"location_type":"CROSS_STREET","location_x":"Covedale Ave and Rapid Run Rd","officer_assignment":"D_3_T","priority":"122","race":"WHITE","sex":"MALE"},
    {"action_taken_cid":"NONE","age_range_cid":"0-17","data_source":"AXON RMS","district":"CP3","event_number":"CPD260426001213","field_subject_cid":"PEDESTRIAN","instance_id":"7f5f4bdc-195b-496b-b0c3-846aeab2f9a0","interview_date":"2026-04-27T00:42:00.000","is_juvenile":true,"latitude_x":"39.1584","location_type":"STREET_ADDRESS","location_x":"42XX President Dr Cincinnati, OH","longitude_x":"-84.5582","officer_assignment":"D_3_P","priority":"124","race":"BLACK_OR_AFRICAN_AMERICAN","sex":"MALE","sna_neighborhood":"Roll Hill"},
    {"action_taken_cid":"NONE","age_range_cid":"26-35","data_source":"AXON RMS","district":"CP3","event_number":"CPD260426001213","field_subject_cid":"PEDESTRIAN","instance_id":"7f5f4bdc-195b-496b-b0c3-846aeab2f9a0","interview_date":"2026-04-27T00:42:00.000","is_juvenile":false,"latitude_x":"39.1528","location_type":"STREET_ADDRESS","location_x":"42XX President Dr Cincinnati, OH","longitude_x":"-84.5586","officer_assignment":"D_3_P","priority":"124","race":"BLACK_OR_AFRICAN_AMERICAN","sex":"FEMALE","sna_neighborhood":"Roll Hill"},
    {"action_taken_cid":"CITATION_MISD","age_range_cid":"26-35","data_source":"AXON RMS","district":"CBS","event_number":"CPD260426001171","field_subject_cid":"PEDESTRIAN","instance_id":"26703099-ec6a-40a3-8ba5-198cfcc54eb7","interview_date":"2026-04-26T23:08:00.000","is_juvenile":false,"latitude_x":"39.1111","location_type":"STREET_ADDRESS","location_x":"8XX Walnut St Cincinnati, OH","longitude_x":"-84.5126","officer_assignment":"CB_B","priority":"122","race":"BLACK_OR_AFRICAN_AMERICAN","sex":"FEMALE","sna_neighborhood":"Downtown"},
    {"action_taken_cid":"WARNING","age_range_cid":"0-17","data_source":"AXON RMS","district":"CP3","event_number":"CPD260426001000","field_subject_cid":"PEDESTRIAN","instance_id":"31d83b3c-d1f4-42b8-9d47-87ac50323342","interview_date":"2026-04-26T21:30:00.000","is_juvenile":true,"latitude_x":"39.1287","location_type":"STREET_ADDRESS","location_x":"15XX Tremont St Cincinnati, OH","longitude_x":"-84.5475","priority":"122","race":"BLACK_OR_AFRICAN_AMERICAN","sex":"MALE","sna_neighborhood":"South Fairmount"},
    {"action_taken_cid":"WARNING","age_range_cid":"26-35","data_source":"AXON RMS","district":"CP1","event_number":"CPD260426000911","field_subject_cid":"PEDESTRIAN","instance_id":"e7a3d890-ab84-4ef7-b23e-b6ddceadbb25","interview_date":"2026-04-26T21:13:00.000","is_juvenile":false,"latitude_x":"39.1175","location_type":"STREET_ADDRESS","location_x":"XX E Liberty St Cincinnati, OH","longitude_x":"-84.5153","officer_assignment":"D_1_S","priority":"125","race":"BLACK_OR_AFRICAN_AMERICAN","sex":"MALE","sna_neighborhood":"Over-the-Rhine"},
    {"action_taken_cid":"WARNING","age_range_cid":"0-17","data_source":"AXON RMS","district":"CP2","event_number":"CPD260426000798","field_subject_cid":"PEDESTRIAN","instance_id":"9c63073e-8e18-4d15-b527-a94f533b2254","interview_date":"2026-04-26T18:28:00.000","is_juvenile":true,"location_type":"STREET_ADDRESS","location_x":"63XX Madison Rd Cincinnati, OH","officer_assignment":"D_2_S","priority":"122","race":"BLACK_OR_AFRICAN_AMERICAN","sex":"MALE"},
    {"action_taken_cid":"WARNING","age_range_cid":"18-25","data_source":"AXON RMS","district":"CP2","event_number":"CPD260426000798","field_subject_cid":"PEDESTRIAN","instance_id":"9c63073e-8e18-4d15-b527-a94f533b2254","interview_date":"2026-04-26T18:28:00.000","is_juvenile":false,"location_type":"STREET_ADDRESS","location_x":"63XX Madison Rd Cincinnati, OH","officer_assignment":"D_2_S","priority":"122","race":"BLACK","sex":"MALE"},
    {"action_taken_cid":"CITATION_MISD","age_range_cid":"46+","data_source":"AXON RMS","district":"CBS","event_number":"CPD260426000821","field_subject_cid":"PEDESTRIAN","instance_id":"42bb52e4-d20c-4981-8d5b-00b06d619e10","interview_date":"2026-04-26T18:28:00.000","is_juvenile":false,"latitude_x":"39.097","location_type":"STREET_ADDRESS","location_x":"4XX E 4th St Cincinnati, OH","longitude_x":"-84.5053","officer_assignment":"CB_B","priority":"124","race":"BLACK_OR_AFRICAN_AMERICAN","sex":"MALE","sna_neighborhood":"Downtown"},
    {"action_taken_cid":"CITATION_CAPIAS_WAR","age_range_cid":"46+","data_source":"AXON RMS","district":"CBS","event_number":"CPD260426000789","field_subject_cid":"PEDESTRIAN","instance_id":"09683179-6b52-41f1-8cdf-7a3f3d3da805","interview_date":"2026-04-26T18:08:00.000","is_juvenile":false,"latitude_x":"39.1535","location_type":"STREET_ADDRESS","location_x":"1XX Main St Cincinnati, OH","longitude_x":"-84.7484","officer_assignment":"CB_B","priority":"122","race":"BLACK_OR_AFRICAN_AMERICAN","sex":"MALE"},
    {"action_taken_cid":"CITATION_TRAFFIC","age_range_cid":"46+","data_source":"AXON RMS","district":"CBS","event_number":"CPD260426000783","field_subject_cid":"PEDESTRIAN","instance_id":"0da4166e-efd3-4c24-9bb0-af342c1d67e3","interview_date":"2026-04-26T18:00:00.000","is_juvenile":false,"location_type":"STREET_ADDRESS","location_x":"XX E 9th St Cincinnati, OH","officer_assignment":"CB_B","priority":"122","race":"BLACK_OR_AFRICAN_AMERICAN","sex":"MALE"},
    {"action_taken_cid":"CITATION_TRAFFIC","age_range_cid":"0-17","data_source":"AXON RMS","district":"CP1","event_number":"CPD260426000683","field_subject_cid":"PEDESTRIAN","instance_id":"31893bad-c4c3-414c-8a67-77ffe7239d2c","interview_date":"2026-04-26T17:04:00.000","is_juvenile":true,"location_type":"CROSS_STREET","location_x":"Linn St and Ezzard Charles Dr","officer_assignment":"D_1_S","priority":"122","race":"BLACK_OR_AFRICAN_AMERICAN","sex":"MALE"},
    {"action_taken_cid":"WARNING","age_range_cid":"0-17","data_source":"AXON RMS","district":"CP1","event_number":"CPD260426000670","field_subject_cid":"PEDESTRIAN","instance_id":"059792e8-fe39-490d-b443-b76a5e209c8b","interview_date":"2026-04-26T16:51:00.000","is_juvenile":true,"location_type":"CROSS_STREET","location_x":"Clark St and Cutter St","officer_assignment":"D_1_S","priority":"122","race":"BLACK_OR_AFRICAN_AMERICAN","sex":"MALE"},
    {"action_taken_cid":"WARNING","age_range_cid":"18-25","data_source":"AXON RMS","district":"CP1","event_number":"CPD260426000670","field_subject_cid":"PEDESTRIAN","instance_id":"059792e8-fe39-490d-b443-b76a5e209c8b","interview_date":"2026-04-26T16:51:00.000","is_juvenile":false,"location_type":"CROSS_STREET","location_x":"Clark St and Cutter St","officer_assignment":"D_1_S","priority":"122","race":"BLACK_OR_AFRICAN_AMERICAN","sex":"MALE"},
    {"action_taken_cid":"NONE","age_range_cid":"46+","data_source":"AXON RMS","district":"CP2","event_number":"CPD260426000476","field_subject_cid":"PEDESTRIAN","instance_id":"d0e05578-f83d-40a9-ba21-0be06f281103","interview_date":"2026-04-26T14:25:00.000","is_juvenile":false,"latitude_x":"39.1216","location_type":"STREET_ADDRESS","location_x":"25XX Park Ave Cincinnati, OH","longitude_x":"-84.4859","officer_assignment":"D_2_F","priority":"124","race":"BLACK_OR_AFRICAN_AMERICAN","sex":"MALE","sna_neighborhood":"Walnut Hills"},
    {"action_taken_cid":"NONE","age_range_cid":"18-25","data_source":"AXON RMS","district":"CP4","event_number":"CPD260426000313","field_subject_cid":"PEDESTRIAN","instance_id":"6dda7729-1c95-46a5-9578-5f09c1b2fd2d","interview_date":"2026-04-26T09:22:00.000","is_juvenile":false,"latitude_x":"39.1986","location_type":"STREET_ADDRESS","location_x":"78XX Dawn Rd Cincinnati, OH","longitude_x":"-84.4619","officer_assignment":"D_4_T","priority":"123","race":"BLACK_OR_AFRICAN_AMERICAN","sex":"MALE","sna_neighborhood":"Roselawn"},
    {"action_taken_cid":"ARREST_MISD","age_range_cid":"18-25","data_source":"AXON RMS","district":"CP1","event_number":"CPD260426000052","field_subject_cid":"PEDESTRIAN","instance_id":"c05937fa-00bb-4650-99c9-6013dff63cf8","interview_date":"2026-04-26T06:47:00.000","is_juvenile":false,"location_type":"STREET_ADDRESS","location_x":"3XX Calhoun St Cincinnati, OH","officer_assignment":"D_1_T","priority":"124","race":"WHITE","sex":"FEMALE"},
    {"action_taken_cid":"NONE","age_range_cid":"0-17","data_source":"AXON RMS","district":"CP1","event_number":"CPD260425001699","field_subject_cid":"PEDESTRIAN","instance_id":"afa36bd8-f795-4f7a-931c-621182e0dcd3","interview_date":"2026-04-26T03:08:00.000","is_juvenile":true,"latitude_x":"39.1112","location_type":"STREET_ADDRESS","location_x":"12XX Broadway St Cincinnati, OH","longitude_x":"-84.5081","officer_assignment":"D_1_T","priority":"122","race":"BLACK_OR_AFRICAN_AMERICAN","sex":"MALE","sna_neighborhood":"Pendleton"},
    {"action_taken_cid":"WARNING","age_range_cid":"0-17","data_source":"AXON RMS","district":"CBS","event_number":"CPD260425001390","field_subject_cid":"PEDESTRIAN","instance_id":"63c88613-f2f9-4d4c-a5c4-1f910e737ada","interview_date":"2026-04-25T23:30:00.000","is_juvenile":true,"location_type":"CROSS_STREET","location_x":"5th St and Walnut St","officer_assignment":"CB_B","priority":"125","race":"BLACK_OR_AFRICAN_AMERICAN","sex":"MALE"},
    {"action_taken_cid":"WARNING","age_range_cid":"0-17","data_source":"AXON RMS","district":"CBS","event_number":"CPD260425001390","field_subject_cid":"PEDESTRIAN","instance_id":"63c88613-f2f9-4d4c-a5c4-1f910e737ada","interview_date":"2026-04-25T23:30:00.000","is_juvenile":true,"location_type":"CROSS_STREET","location_x":"5th St and Walnut St","officer_assignment":"CB_B","priority":"125","race":"BLACK_OR_AFRICAN_AMERICAN","sex":"FEMALE"},
    {"action_taken_cid":"WARNING","age_range_cid":"36-45","data_source":"AXON RMS","district":"CP1","event_number":"CPD260425001171","field_subject_cid":"PEDESTRIAN","instance_id":"028e96d4-a261-425f-ba32-b432989166e6","interview_date":"2026-04-25T20:57:00.000","is_juvenile":false,"location_type":"CROSS_STREET","location_x":"Race St and Liberty St","officer_assignment":"D_1_S","priority":"122","race":"BLACK_OR_AFRICAN_AMERICAN","sex":"MALE"},
    {"action_taken_cid":"WARNING","age_range_cid":"26-35","data_source":"AXON RMS","district":"CP1","event_number":"CPD260425001113","field_subject_cid":"PEDESTRIAN","instance_id":"5421c494-6fc3-41f9-ae7a-44294c3efcd4","interview_date":"2026-04-25T20:21:00.000","is_juvenile":false,"location_type":"CROSS_STREET","location_x":"Walnut St and McMicken Ave","officer_assignment":"D_1_S","priority":"122","race":"BLACK_OR_AFRICAN_AMERICAN","sex":"MALE"},
    {"action_taken_cid":"NONE","age_range_cid":"26-35","data_source":"AXON RMS","district":"CP3","event_number":"CPD260425000835","field_subject_cid":"PEDESTRIAN","instance_id":"d2af48ec-a683-4e06-9d7b-85e8da9dc610","interview_date":"2026-04-25T17:03:00.000","is_juvenile":false,"location_type":"STREET_ADDRESS","location_x":"30XX Queen City Ave Cincinnati, OH","officer_assignment":"D_3_S","priority":"123","race":"WHITE","sex":"MALE"},
    {"action_taken_cid":"NONE","age_range_cid":"36-45","data_source":"AXON RMS","district":"CBS","event_number":"CPD260425000597","field_subject_cid":"PEDESTRIAN","instance_id":"225237bc-8ec0-4a57-83fd-535646506f2c","interview_date":"2026-04-25T14:45:00.000","is_juvenile":false,"location_type":"CROSS_STREET","location_x":"Court St and Walnut St","officer_assignment":"CB_B","priority":"122","race":"WHITE","sex":"MALE"},
    {"action_taken_cid":"WARNING","age_range_cid":"36-45","data_source":"AXON RMS","district":"CBS","event_number":"CPD260425000450","field_subject_cid":"PEDESTRIAN","instance_id":"5f8f42a1-68a6-47f3-bdb1-1dd46faa5a55","interview_date":"2026-04-25T12:21:00.000","is_juvenile":false,"location_type":"CROSS_STREET","location_x":"4th St and Main St","officer_assignment":"CB_B","priority":"122","race":"WHITE","sex":"MALE"},
    {"action_taken_cid":"WARNING","age_range_cid":"36-45","data_source":"AXON RMS","district":"CBS","event_number":"CPD260425000440","field_subject_cid":"PEDESTRIAN","instance_id":"f32d3ac2-7baa-4d79-92d2-a35ea0699600","interview_date":"2026-04-25T12:14:00.000","is_juvenile":false,"location_type":"CROSS_STREET","location_x":"Court St and Walnut St","officer_assignment":"CB_B","priority":"122","race":"BLACK_OR_AFRICAN_AMERICAN","sex":"MALE"},
    {"action_taken_cid":"NONE","age_range_cid":"46+","data_source":"AXON RMS","district":"CP4","event_number":"CPD260424001820","field_subject_cid":"PEDESTRIAN","instance_id":"c701e5c4-3949-44db-97e0-85babd64f2fe","interview_date":"2026-04-25T03:01:00.000","is_juvenile":false,"latitude_x":"39.153","location_type":"STREET_ADDRESS","location_x":"6XX Rockdale Ave Cincinnati, OH","longitude_x":"-84.4931","officer_assignment":"D_4_T","priority":"124","race":"WHITE","sex":"MALE","sna_neighborhood":"Avondale"},
    {"action_taken_cid":"WARNING","age_range_cid":"18-25","data_source":"AXON RMS","district":"CBS","event_number":"CPD260424001281","field_subject_cid":"PEDESTRIAN","instance_id":"cf068cab-87c6-4c7a-bdb7-55cb2eb8c9ba","interview_date":"2026-04-24T20:10:00.000","is_juvenile":false,"latitude_x":"39.1075","location_type":"STREET_ADDRESS","location_x":"1XX Garfield Pl Cincinnati, OH","longitude_x":"-84.5163","officer_assignment":"CB_B","priority":"125","race":"WHITE","sex":"FEMALE","sna_neighborhood":"Downtown"},
    {"action_taken_cid":"CITATION_MISD","age_range_cid":"36-45","data_source":"AXON RMS","district":"CBS","event_number":"CPD260424001061","field_subject_cid":"PEDESTRIAN","instance_id":"19553ee7-2c66-42a8-9632-bb642b091d19","interview_date":"2026-04-24T19:15:00.000","is_juvenile":false,"location_type":"CROSS_STREET","location_x":"4th St and Main St","officer_assignment":"CB_B","priority":"122","race":"BLACK_OR_AFRICAN_AMERICAN","sex":"MALE"},
    {"action_taken_cid":"CITATION_MISD","age_range_cid":"46+","data_source":"AXON RMS","district":"CBS","event_number":"CPD260424001061","field_subject_cid":"PEDESTRIAN","instance_id":"19553ee7-2c66-42a8-9632-bb642b091d19","interview_date":"2026-04-24T19:15:00.000","is_juvenile":false,"location_type":"CROSS_STREET","location_x":"4th St and Main St","officer_assignment":"CB_B","priority":"122","race":"WHITE","sex":"MALE"},
    {"action_taken_cid":"WARNING","age_range_cid":"46+","data_source":"AXON RMS","district":"CBS","event_number":"CPD260424000921","field_subject_cid":"PEDESTRIAN","instance_id":"e8b22b51-da69-4bb4-98a0-dee6f3166fad","interview_date":"2026-04-24T18:10:00.000","is_juvenile":false,"latitude_x":"39.1033","location_type":"STREET_ADDRESS","location_x":"10XX Main St Cincinnati, OH","longitude_x":"-84.5108","officer_assignment":"CB_B","priority":"122","race":"BLACK_OR_AFRICAN_AMERICAN","sex":"MALE","sna_neighborhood":"Downtown"},
    {"action_taken_cid":"NONE","age_range_cid":"36-45","data_source":"AXON RMS","district":"CP2","event_number":"CPD260424000784","field_subject_cid":"PEDESTRIAN","instance_id":"db9c4986-c2ad-45b0-b629-21e0694bd2d8","interview_date":"2026-04-24T17:16:00.000","is_juvenile":false,"location_type":"MILE_MARKER","location_x":"Wasson Way Trai 4.4","officer_assignment":"D_2_S","priority":"124","race":"WHITE","sex":"MALE"},
    {"action_taken_cid":"WARNING","age_range_cid":"18-25","data_source":"AXON RMS","district":"CP3","event_number":"CPD260424000720","field_subject_cid":"PEDESTRIAN","instance_id":"27b4f665-4528-497a-ac83-e970edad6549","interview_date":"2026-04-24T16:25:00.000","is_juvenile":false,"latitude_x":"39.1575","location_type":"STREET_ADDRESS","location_x":"15XX Chase Ave Cincinnati, OH","longitude_x":"-84.5399","officer_assignment":"D_3_VCS","priority":"125","race":"BLACK_OR_AFRICAN_AMERICAN","sex":"MALE","sna_neighborhood":"Northside"},
    {"action_taken_cid":"WARNING","age_range_cid":"18-25","data_source":"AXON RMS","district":"CP3","event_number":"CPD260424000720","field_subject_cid":"PEDESTRIAN","instance_id":"27b4f665-4528-497a-ac83-e970edad6549","interview_date":"2026-04-24T16:25:00.000","is_juvenile":false,"latitude_x":"39.165","location_type":"STREET_ADDRESS","location_x":"15XX Chase Ave Cincinnati, OH","longitude_x":"-84.5388","officer_assignment":"D_3_VCS","priority":"125","race":"ASIAN","sex":"MALE","sna_neighborhood":"Northside"},
    {"action_taken_cid":"CITATION_CAPIAS_WAR","age_range_cid":"26-35","data_source":"AXON RMS","district":"CBS","event_number":"CPD260424000511","field_subject_cid":"PEDESTRIAN","instance_id":"320b3ede-5e24-4cb2-90b6-d64672027201","interview_date":"2026-04-24T14:30:00.000","is_juvenile":false,"location_type":"CROSS_STREET","location_x":"Race St and Freedom Way","officer_assignment":"CB_B","priority":"122","race":"BLACK_OR_AFRICAN_AMERICAN","sex":"MALE"},
    {"action_taken_cid":"NONE","age_range_cid":"0-17","data_source":"AXON RMS","district":"CBS","event_number":"CPD260423001542","field_subject_cid":"PEDESTRIAN","instance_id":"9e89e776-6c4c-4f9e-9029-d088ec13152e","interview_date":"2026-04-23T23:54:00.000","is_juvenile":true,"latitude_x":"39.1047","location_type":"STREET_ADDRESS","location_x":"1XX E Freedom Way Cincinnati, OH","longitude_x":"-84.51","officer_assignment":"CB_B","priority":"125","race":"BLACK_OR_AFRICAN_AMERICAN","sex":"FEMALE","sna_neighborhood":"Downtown"},
    {"action_taken_cid":"NONE","age_range_cid":"18-25","data_source":"AXON RMS","district":"CBS","event_number":"CPD260423001542","field_subject_cid":"PEDESTRIAN","instance_id":"9e89e776-6c4c-4f9e-9029-d088ec13152e","interview_date":"2026-04-23T23:54:00.000","is_juvenile":false,"latitude_x":"39.1047","location_type":"STREET_ADDRESS","location_x":"1XX E Freedom Way Cincinnati, OH","longitude_x":"-84.5108","officer_assignment":"CB_B","priority":"125","race":"BLACK_OR_AFRICAN_AMERICAN","sex":"FEMALE","sna_neighborhood":"Downtown"},
    {"action_taken_cid":"NONE","age_range_cid":"18-25","data_source":"AXON RMS","district":"CBS","event_number":"CPD260423001542","field_subject_cid":"PEDESTRIAN","instance_id":"9e89e776-6c4c-4f9e-9029-d088ec13152e","interview_date":"2026-04-23T23:54:00.000","is_juvenile":false,"latitude_x":"39.1053","location_type":"STREET_ADDRESS","location_x":"1XX E Freedom Way Cincinnati, OH","longitude_x":"-84.51","officer_assignment":"CB_B","priority":"125","race":"BLACK_OR_AFRICAN_AMERICAN","sex":"FEMALE","sna_neighborhood":"Downtown"},
    {"action_taken_cid":"NONE","age_range_cid":"0-17","data_source":"AXON RMS","district":"CP3","event_number":"CPD260423000895","field_subject_cid":"PEDESTRIAN","instance_id":"82dc4f14-0e11-44ad-bad6-91f48f86d93f","interview_date":"2026-04-23T20:49:00.000","is_juvenile":true,"location_type":"STREET_ADDRESS","location_x":"42XX Hamilton Ave Cincinnati, OH","priority":"125","race":"BLACK","sex":"MALE"},
    {"action_taken_cid":"WARNING","age_range_cid":"0-17","data_source":"AXON RMS","district":"CP2","event_number":"CPD260423001218","field_subject_cid":"PEDESTRIAN","instance_id":"987eea3d-531e-48b3-8580-deeca4b0c640","interview_date":"2026-04-23T20:48:00.000","is_juvenile":true,"latitude_x":"39.1656","location_type":"STREET_ADDRESS","location_x":"33XX Ibsen Ave Cincinnati, OH","longitude_x":"-84.4229","priority":"122","race":"BLACK_OR_AFRICAN_AMERICAN","sex":"MALE","sna_neighborhood":"Oakley"},
    {"action_taken_cid":"WARNING","age_range_cid":"0-17","data_source":"AXON RMS","district":"CP2","event_number":"CPD260423001218","field_subject_cid":"PEDESTRIAN","instance_id":"987eea3d-531e-48b3-8580-deeca4b0c640","interview_date":"2026-04-23T20:48:00.000","is_juvenile":true,"latitude_x":"39.1631","location_type":"STREET_ADDRESS","location_x":"33XX Ibsen Ave Cincinnati, OH","longitude_x":"-84.4237","priority":"122","race":"BLACK_OR_AFRICAN_AMERICAN","sex":"MALE","sna_neighborhood":"Oakley"},
    {"action_taken_cid":"WARNING","age_range_cid":"0-17","data_source":"AXON RMS","district":"CP2","event_number":"CPD260423001218","field_subject_cid":"PEDESTRIAN","instance_id":"987eea3d-531e-48b3-8580-deeca4b0c640","interview_date":"2026-04-23T20:48:00.000","is_juvenile":true,"latitude_x":"39.1605","location_type":"STREET_ADDRESS","location_x":"33XX Ibsen Ave Cincinnati, OH","longitude_x":"-84.4233","priority":"122","race":"BLACK_OR_AFRICAN_AMERICAN","sex":"MALE","sna_neighborhood":"Oakley"},
    {"action_taken_cid":"CITATION_TRAFFIC","age_range_cid":"26-35","data_source":"AXON RMS","district":"CBS","event_number":"CPD260423001026","field_subject_cid":"PEDESTRIAN","instance_id":"ad6b2535-1883-4805-9378-1b14ac9e5622","interview_date":"2026-04-23T19:10:00.000","is_juvenile":false,"latitude_x":"39.1066","location_type":"STREET_ADDRESS","location_x":"6XX Main St Cincinnati, OH","longitude_x":"-84.5102","officer_assignment":"CB_B","priority":"122","race":"BLACK_OR_AFRICAN_AMERICAN","sex":"MALE","sna_neighborhood":"Downtown"},
    {"action_taken_cid":"ARREST_CAPIAS_WAR","age_range_cid":"46+","data_source":"AXON RMS","district":"CBS","event_number":"CPD260423000988","field_subject_cid":"PEDESTRIAN","instance_id":"ca067baa-6408-49ee-97ee-b99e55d61f40","interview_date":"2026-04-23T18:50:00.000","is_juvenile":false,"latitude_x":"39.1027","location_type":"STREET_ADDRESS","location_x":"6XX Main St Cincinnati, OH","longitude_x":"-84.5108","officer_assignment":"CB_B","priority":"122","race":"WHITE","sex":"FEMALE","sna_neighborhood":"Downtown"},
    {"action_taken_cid":"CITATION_CAPIAS_WAR","age_range_cid":"46+","data_source":"AXON RMS","district":"CBS","event_number":"CPD260423000988","field_subject_cid":"PEDESTRIAN","instance_id":"ca067baa-6408-49ee-97ee-b99e55d61f40","interview_date":"2026-04-23T18:50:00.000","is_juvenile":false,"latitude_x":"39.0975","location_type":"STREET_ADDRESS","location_x":"6XX Main St Cincinnati, OH","longitude_x":"-84.5112","officer_assignment":"CB_B","priority":"122","race":"WHITE","sex":"MALE","sna_neighborhood":"Downtown"},
    {"action_taken_cid":"OTHER","age_range_cid":"18-25","data_source":"AXON RMS","district":"CBS","event_number":"CPD260423000886","field_subject_cid":"PEDESTRIAN","instance_id":"376fe865-592e-48cf-8535-dcda5a8466ef","interview_date":"2026-04-23T18:11:00.000","is_juvenile":false,"latitude_x":"39.1033","location_type":"STREET_ADDRESS","location_x":"XX W Freedom Way Cincinnati, OH","longitude_x":"-84.5118","officer_assignment":"CB_B","priority":"122","race":"WHITE","sex":"MALE","sna_neighborhood":"Downtown"},
    {"action_taken_cid":"WARNING","age_range_cid":"18-25","data_source":"AXON RMS","district":"CBS","event_number":"CPD260423000832","field_subject_cid":"PEDESTRIAN","instance_id":"71d700e9-14fd-4108-b57e-6c8f7fcb6661","interview_date":"2026-04-23T17:30:00.000","is_juvenile":false,"location_type":"CROSS_STREET","location_x":"9th St and Vine St","officer_assignment":"CB_B","priority":"122","race":"BLACK_OR_AFRICAN_AMERICAN","sex":"MALE"},
    {"action_taken_cid":"CITATION_TRAFFIC","age_range_cid":"26-35","data_source":"AXON RMS","district":"CBS","event_number":"CPD260423000557","field_subject_cid":"PEDESTRIAN","instance_id":"c4ee0212-4e8a-4f1f-8de3-676ac09c2397","interview_date":"2026-04-23T15:29:00.000","is_juvenile":false,"location_type":"MILE_MARKER","location_x":"NB I-71 1","officer_assignment":"TRA","priority":"123","race":"WHITE","sex":"MALE"},
    {"action_taken_cid":"NONE","age_range_cid":"0-17","data_source":"AXON RMS","district":"CP2","event_number":"CPD260423000456","field_subject_cid":"PEDESTRIAN","instance_id":"8ccce8d7-b771-4feb-99ee-95dfcf49c273","interview_date":"2026-04-23T14:20:00.000","is_juvenile":true,"latitude_x":"39.1718","location_type":"STREET_ADDRESS","location_x":"50XX E Eastwood Cir Cincinnati, OH","longitude_x":"-84.4109","officer_assignment":"YSU","priority":"122","race":"BLACK","sex":"MALE","sna_neighborhood":"Madisonville"},
    {"action_taken_cid":"OTHER","age_range_cid":"18-25","data_source":"AXON RMS","district":"CP2","event_number":"CPD260423000456","field_subject_cid":"PEDESTRIAN","instance_id":"8ccce8d7-b771-4feb-99ee-95dfcf49c273","interview_date":"2026-04-23T14:20:00.000","is_juvenile":false,"latitude_x":"39.1555","location_type":"STREET_ADDRESS","location_x":"50XX E Eastwood Cir Cincinnati, OH","longitude_x":"-84.4097","officer_assignment":"YSU","priority":"122","race":"BLACK","sex":"FEMALE","sna_neighborhood":"Madisonville"},
    {"action_taken_cid":"NONE","age_range_cid":"36-45","data_source":"AXON RMS","district":"CP3","event_number":"CPD260423000161","field_subject_cid":"PEDESTRIAN","instance_id":"75850086-cdc1-4681-bdd7-7b2895c2bdc2","interview_date":"2026-04-23T10:55:00.000","is_juvenile":false,"location_type":"STREET_ADDRESS","location_x":"37XX Saint Lawrence  Cincinnati, OH","priority":"122","race":"WHITE","sex":"MALE"},
    {"action_taken_cid":"NONE","age_range_cid":"26-35","data_source":"AXON RMS","district":"CP3","event_number":"CPD260423000161","field_subject_cid":"PEDESTRIAN","instance_id":"def70f70-af4e-42be-ba16-99972ace0716","interview_date":"2026-04-23T10:53:00.000","is_juvenile":false,"location_type":"STREET_ADDRESS","location_x":"37XX Saint Lawrence  Cincinnati, OH","officer_assignment":"D_3_T","priority":"122","race":"BLACK_OR_AFRICAN_AMERICAN","sex":"MALE"},
    {"action_taken_cid":"NONE","age_range_cid":"36-45","data_source":"AXON RMS","district":"CP2","event_number":"CPD260422001829","field_subject_cid":"PEDESTRIAN","instance_id":"9693a050-0758-48e4-b582-67833085b370","interview_date":"2026-04-23T03:36:00.000","is_juvenile":false,"latitude_x":"39.1282","location_type":"STREET_ADDRESS","location_x":"22XX Boone St Cincinnati, OH","longitude_x":"-84.4974","priority":"122","race":"BLACK_OR_AFRICAN_AMERICAN","sex":"MALE","sna_neighborhood":"Walnut Hills"},
    {"action_taken_cid":"ARREST_MISD","age_range_cid":"36-45","data_source":"AXON RMS","district":"CP2","event_number":"CPD260422001829","field_subject_cid":"PEDESTRIAN","instance_id":"9693a050-0758-48e4-b582-67833085b370","interview_date":"2026-04-23T03:36:00.000","is_juvenile":false,"latitude_x":"39.1298","location_type":"STREET_ADDRESS","location_x":"22XX Boone St Cincinnati, OH","longitude_x":"-84.4963","priority":"122","race":"BLACK_OR_AFRICAN_AMERICAN","sex":"MALE","sna_neighborhood":"Walnut Hills"},
    {"action_taken_cid":"WARNING","age_range_cid":"46+","data_source":"AXON RMS","district":"CP4","event_number":"CPD260422001827","field_subject_cid":"PEDESTRIAN","instance_id":"5088add2-cf35-4efa-843d-5c925411a083","interview_date":"2026-04-23T02:35:00.000","is_juvenile":false,"latitude_x":"39.1421","location_type":"STREET_ADDRESS","location_x":"35XX Reading Rd Cincinnati, OH","longitude_x":"-84.4896","officer_assignment":"D_4_T","priority":"123","race":"WHITE","sex":"MALE","sna_neighborhood":"Avondale"},
    {"action_taken_cid":"ARREST_FELONY","age_range_cid":"46+","data_source":"AXON RMS","district":"CBS","event_number":"CPD260422001300","field_subject_cid":"PEDESTRIAN","instance_id":"8b0477e8-4f62-4234-a993-2b53a9e53081","interview_date":"2026-04-22T21:09:00.000","is_juvenile":false,"latitude_x":"39.1073","location_type":"STREET_ADDRESS","location_x":"5XX Walnut St Cincinnati, OH","longitude_x":"-84.511","officer_assignment":"CB_B","priority":"122","race":"WHITE","sex":"MALE","sna_neighborhood":"Downtown"},
    {"action_taken_cid":"WARNING","age_range_cid":"26-35","data_source":"AXON RMS","district":"CBS","event_number":"CPD260422001300","field_subject_cid":"PEDESTRIAN","instance_id":"8b0477e8-4f62-4234-a993-2b53a9e53081","interview_date":"2026-04-22T21:09:00.000","is_juvenile":false,"latitude_x":"39.0976","location_type":"STREET_ADDRESS","location_x":"5XX Walnut St Cincinnati, OH","longitude_x":"-84.5102","officer_assignment":"CB_B","priority":"122","race":"WHITE","sex":"MALE","sna_neighborhood":"Downtown"},
    {"action_taken_cid":"ARREST_MISD","age_range_cid":"26-35","data_source":"AXON RMS","district":"CBS","event_number":"CPD260422001093","field_subject_cid":"PEDESTRIAN","instance_id":"628cf346-4e30-4c04-9cae-13e5c7ea5300","interview_date":"2026-04-22T19:25:00.000","is_juvenile":false,"latitude_x":"39.1048","location_type":"STREET_ADDRESS","location_x":"XX Garfield Pl Cincinnati, OH","longitude_x":"-84.5153","officer_assignment":"CB_B","priority":"125","race":"WHITE","sex":"MALE","sna_neighborhood":"Downtown"},
    {"action_taken_cid":"CITATION_MISD","age_range_cid":"26-35","data_source":"AXON RMS","district":"CBS","event_number":"CPD260422001040","field_subject_cid":"PEDESTRIAN","instance_id":"69ee51c1-0d0b-4411-96ff-fa4c8ef8cc51","interview_date":"2026-04-22T19:00:00.000","is_juvenile":false,"location_type":"CROSS_STREET","location_x":"6th St and Main St","officer_assignment":"CB_B","priority":"122","race":"BLACK_OR_AFRICAN_AMERICAN","sex":"MALE"},
    {"action_taken_cid":"CITATION_MISD","age_range_cid":"36-45","data_source":"AXON RMS","district":"CBS","event_number":"CPD260422001018","field_subject_cid":"PEDESTRIAN","instance_id":"52c73064-18d1-46a4-a366-9a7a34b3fb37","interview_date":"2026-04-22T18:25:00.000","is_juvenile":false,"latitude_x":"39.1118","location_type":"STREET_ADDRESS","location_x":"8XX Main St Cincinnati, OH","longitude_x":"-84.5106","officer_assignment":"CB_B","priority":"122","race":"BLACK_OR_AFRICAN_AMERICAN","sex":"MALE","sna_neighborhood":"Downtown"},
    {"action_taken_cid":"WARNING","age_range_cid":"26-35","data_source":"AXON RMS","district":"CP1","event_number":"CPD260422000730","field_subject_cid":"PEDESTRIAN","instance_id":"91900124-b348-4c62-b967-084c316bc733","interview_date":"2026-04-22T16:28:00.000","is_juvenile":false,"latitude_x":"39.1138","location_type":"STREET_ADDRESS","location_x":"16XX Walnut St Cincinnati, OH","longitude_x":"-84.5136","officer_assignment":"PV","priority":"125","race":"BLACK_OR_AFRICAN_AMERICAN","sex":"MALE","sna_neighborhood":"Over-the-Rhine"},
    {"action_taken_cid":"WARNING","age_range_cid":"36-45","data_source":"AXON RMS","district":"CP2","event_number":"CPD260421001493","field_subject_cid":"PEDESTRIAN","instance_id":"aa38361b-2567-4615-ae70-0caadc2288a3","interview_date":"2026-04-21T23:09:00.000","is_juvenile":false,"latitude_x":"39.1221","location_type":"STREET_ADDRESS","location_x":"23XX Gilbert Ave Cincinnati, OH","longitude_x":"-84.4924","officer_assignment":"PV","priority":"122","race":"BLACK_OR_AFRICAN_AMERICAN","sex":"MALE","sna_neighborhood":"Walnut Hills"},
    {"action_taken_cid":"WARNING","age_range_cid":"26-35","data_source":"AXON RMS","district":"CP2","event_number":"CPD260421001493","field_subject_cid":"PEDESTRIAN","instance_id":"aa38361b-2567-4615-ae70-0caadc2288a3","interview_date":"2026-04-21T23:09:00.000","is_juvenile":false,"latitude_x":"39.1249","location_type":"STREET_ADDRESS","location_x":"23XX Gilbert Ave Cincinnati, OH","longitude_x":"-84.4914","officer_assignment":"PV","priority":"122","race":"BLACK_OR_AFRICAN_AMERICAN","sex":"MALE","sna_neighborhood":"Walnut Hills"},
    {"action_taken_cid":"CITATION_MISD","age_range_cid":"18-25","data_source":"AXON RMS","district":"CP2","event_number":"CPD260421001406","field_subject_cid":"PEDESTRIAN","instance_id":"872623c6-7cd4-44b4-9e95-d6601cbdc719","interview_date":"2026-04-21T22:31:00.000","is_juvenile":false,"latitude_x":"39.1323","location_type":"STREET_ADDRESS","location_x":"29XX Gilbert Ave Cincinnati, OH","longitude_x":"-84.4882","officer_assignment":"D_2_S","priority":"125","race":"BLACK_OR_AFRICAN_AMERICAN","sex":"MALE","sna_neighborhood":"Walnut Hills"},
    {"action_taken_cid":"CITATION_MISD","age_range_cid":"26-35","data_source":"AXON RMS","district":"CP1","event_number":"CPD260421001289","field_subject_cid":"PEDESTRIAN","instance_id":"7510bf1b-728f-4eb9-bc8b-986911800f9f","interview_date":"2026-04-21T21:00:00.000","is_juvenile":false,"latitude_x":"39.1105","location_type":"STREET_ADDRESS","location_x":"12XX Walnut St Cincinnati, OH","longitude_x":"-84.5129","officer_assignment":"D_1_VCS","priority":"122","race":"BLACK_OR_AFRICAN_AMERICAN","sex":"MALE","sna_neighborhood":"Over-the-Rhine"},
    {"action_taken_cid":"WARNING","age_range_cid":"26-35","data_source":"AXON RMS","district":"CP1","event_number":"CPD260421001137","field_subject_cid":"PEDESTRIAN","instance_id":"539d3822-38df-4d42-a00d-adb18dce4685","interview_date":"2026-04-21T19:59:00.000","is_juvenile":false,"latitude_x":"39.1127","location_type":"STREET_ADDRESS","location_x":"12XX Walnut St Cincinnati, OH","longitude_x":"-84.513","officer_assignment":"D_1_VCS","priority":"122","race":"BLACK_OR_AFRICAN_AMERICAN","sex":"MALE","sna_neighborhood":"Over-the-Rhine"},
    {"action_taken_cid":"CITATION_MISD","age_range_cid":"46+","data_source":"AXON RMS","district":"CP2","event_number":"CPD260421000987","field_subject_cid":"PEDESTRIAN","instance_id":"e09183ae-15fd-49b1-b551-6ed56533b53a","interview_date":"2026-04-21T19:00:00.000","is_juvenile":false,"latitude_x":"39.0969","location_type":"STREET_ADDRESS","location_x":"22XX Oxford Ave Cincinnati, OH","longitude_x":"-84.3877","officer_assignment":"D_2_S","priority":"121","race":"WHITE","sex":"MALE","sna_neighborhood":"Mt. Washington"},
    {"action_taken_cid":"WARNING","age_range_cid":"46+","data_source":"AXON RMS","district":"CP2","event_number":"CPD260421000540","field_subject_cid":"PEDESTRIAN","instance_id":"88d012e3-c770-4ef8-ab25-7c256138129c","interview_date":"2026-04-21T15:24:00.000","is_juvenile":false,"latitude_x":"39.141","location_type":"STREET_ADDRESS","location_x":"30XX Hackberry St Cincinnati, OH","longitude_x":"-84.4744","officer_assignment":"D_2_N","priority":"122","race":"BLACK_OR_AFRICAN_AMERICAN","sex":"MALE","sna_neighborhood":"Evanston"},
    {"action_taken_cid":"ARREST_CAPIAS_WAR","age_range_cid":"46+","data_source":"AXON RMS","district":"CP2","event_number":"CPD260421000540","field_subject_cid":"PEDESTRIAN","instance_id":"88d012e3-c770-4ef8-ab25-7c256138129c","interview_date":"2026-04-21T15:24:00.000","is_juvenile":false,"latitude_x":"39.1416","location_type":"STREET_ADDRESS","location_x":"30XX Hackberry St Cincinnati, OH","longitude_x":"-84.4748","officer_assignment":"D_2_N","priority":"122","race":"WHITE","sex":"FEMALE","sna_neighborhood":"Evanston"},
    {"action_taken_cid":"WARNING","age_range_cid":"0-17","data_source":"AXON RMS","district":"CP2","event_number":"CPD260421000351","field_subject_cid":"PEDESTRIAN","instance_id":"e7e01038-3657-42c7-a023-2dd51b5c0032","interview_date":"2026-04-21T13:36:00.000","is_juvenile":true,"latitude_x":"39.1645","location_type":"STREET_ADDRESS","location_x":"64XX Madison Rd Cincinnati, OH","longitude_x":"-84.3849","officer_assignment":"D_2_F","priority":"124","race":"BLACK_OR_AFRICAN_AMERICAN","sex":"MALE","sna_neighborhood":"Madisonville"},
    {"action_taken_cid":"WARNING","age_range_cid":"0-17","data_source":"AXON RMS","district":"CP2","event_number":"CPD260421000351","field_subject_cid":"PEDESTRIAN","instance_id":"e7e01038-3657-42c7-a023-2dd51b5c0032","interview_date":"2026-04-21T13:36:00.000","is_juvenile":true,"latitude_x":"39.1632","location_type":"STREET_ADDRESS","location_x":"64XX Madison Rd Cincinnati, OH","longitude_x":"-84.3847","officer_assignment":"D_2_F","priority":"124","race":"BLACK_OR_AFRICAN_AMERICAN","sex":"MALE","sna_neighborhood":"Madisonville"},
    {"action_taken_cid":"CITATION_TRAFFIC","age_range_cid":"46+","data_source":"AXON RMS","district":"CBS","event_number":"CPD260421000064","field_subject_cid":"PEDESTRIAN","instance_id":"30ab993a-0c03-4adf-a92e-2b657aaf763d","interview_date":"2026-04-21T06:11:00.000","is_juvenile":false,"location_type":"STREET_ADDRESS","location_x":"7XX Vine St Cincinnati, OH","priority":"125","race":"WHITE","sex":"MALE"},
    {"action_taken_cid":"WARNING","age_range_cid":"0-17","data_source":"AXON RMS","field_subject_cid":"PEDESTRIAN","instance_id":"888948ea-30b4-4c7c-a438-9eea342b57a6","interview_date":"2026-04-21T00:59:00.000","is_juvenile":true,"location_type":"STREET_ADDRESS","location_x":"9XX Race St Cincinnati, OH","officer_assignment":"CB_B","race":"BLACK_OR_AFRICAN_AMERICAN","sex":"MALE"},
    {"action_taken_cid":"WARNING","age_range_cid":"0-17","data_source":"AXON RMS","field_subject_cid":"PEDESTRIAN","instance_id":"888948ea-30b4-4c7c-a438-9eea342b57a6","interview_date":"2026-04-21T00:59:00.000","is_juvenile":true,"location_type":"STREET_ADDRESS","location_x":"9XX Race St Cincinnati, OH","officer_assignment":"CB_B","race":"BLACK_OR_AFRICAN_AMERICAN","sex":"MALE"},
    {"action_taken_cid":"WARNING","age_range_cid":"0-17","data_source":"AXON RMS","field_subject_cid":"PEDESTRIAN","instance_id":"888948ea-30b4-4c7c-a438-9eea342b57a6","interview_date":"2026-04-21T00:59:00.000","is_juvenile":true,"location_type":"STREET_ADDRESS","location_x":"9XX Race St Cincinnati, OH","officer_assignment":"CB_B","race":"BLACK_OR_AFRICAN_AMERICAN","sex":"MALE"},
    {"action_taken_cid":"WARNING","data_source":"AXON RMS","district":"CP4","event_number":"CPD260420001825","field_subject_cid":"PEDESTRIAN","instance_id":"1bd2acdd-1673-4c27-aca0-509a513b4df3","interview_date":"2026-04-21T00:35:00.000","is_juvenile":false,"latitude_x":"39.1533","location_type":"STREET_ADDRESS","location_x":"9XX Dana Ave Cincinnati, OH","longitude_x":"-84.4841","officer_assignment":"PV","priority":"122","race":"BLACK_OR_AFRICAN_AMERICAN","sex":"MALE","sna_neighborhood":"Avondale"},
    {"action_taken_cid":"WARNING","age_range_cid":"46+","data_source":"AXON RMS","district":"CP1","event_number":"CPD260420001662","field_subject_cid":"PEDESTRIAN","instance_id":"472fd2ad-5086-4792-a3ac-e222693ee369","interview_date":"2026-04-20T22:33:00.000","is_juvenile":false,"latitude_x":"39.1115","location_type":"STREET_ADDRESS","location_x":"20XX Eleanor Pl Cincinnati, OH","longitude_x":"-84.512","officer_assignment":"PV","priority":"125","race":"BLACK_OR_AFRICAN_AMERICAN","sex":"MALE","sna_neighborhood":"Mt. Auburn"},
    {"action_taken_cid":"WARNING","age_range_cid":"0-17","data_source":"AXON RMS","district":"CP3","event_number":"CPD260420001578","field_subject_cid":"PEDESTRIAN","instance_id":"aa76dbae-532d-4630-8500-6812258a03f1","interview_date":"2026-04-20T22:12:00.000","is_juvenile":true,"latitude_x":"39.1369","location_type":"STREET_ADDRESS","location_x":"24XX Harrison Ave Newport, KY","longitude_x":"-84.5802","officer_assignment":"D_3_VCS","priority":"122","race":"BLACK_OR_AFRICAN_AMERICAN","sex":"MALE","sna_neighborhood":"Westwood"},
    {"action_taken_cid":"WARNING","age_range_cid":"0-17","data_source":"AXON RMS","district":"CP3","event_number":"CPD260420001578","field_subject_cid":"PEDESTRIAN","instance_id":"aa76dbae-532d-4630-8500-6812258a03f1","interview_date":"2026-04-20T22:12:00.000","is_juvenile":true,"latitude_x":"39.1496","location_type":"STREET_ADDRESS","location_x":"24XX Harrison Ave Newport, KY","longitude_x":"-84.5815","officer_assignment":"D_3_VCS","priority":"122","race":"BLACK_OR_AFRICAN_AMERICAN","sex":"MALE","sna_neighborhood":"Westwood"},
    {"action_taken_cid":"WARNING","age_range_cid":"0-17","data_source":"AXON RMS","district":"CP3","event_number":"CPD260420001578","field_subject_cid":"PEDESTRIAN","instance_id":"f45380a4-df2f-44b8-9ea4-6998aff23f8f","interview_date":"2026-04-20T21:55:00.000","is_juvenile":true,"location_type":"STREET_ADDRESS","location_x":"30XX Bracken Woods L Cincinnati, OH","officer_assignment":"D_3_VCS","priority":"122","race":"BLACK_OR_AFRICAN_AMERICAN","sex":"MALE"},
    {"action_taken_cid":"NONE","age_range_cid":"46+","data_source":"AXON RMS","district":"CP1","event_number":"CPD260420001285","field_subject_cid":"PEDESTRIAN","instance_id":"96a75082-29f6-4c3d-8f4a-4cff9d449b90","interview_date":"2026-04-20T19:53:00.000","is_juvenile":false,"latitude_x":"39.1175","location_type":"STREET_ADDRESS","location_x":"16XX Linn St Cincinnati, OH","longitude_x":"-84.5276","priority":"125","race":"BLACK_OR_AFRICAN_AMERICAN","sex":"MALE","sna_neighborhood":"West End"},
    {"action_taken_cid":"WARNING","age_range_cid":"46+","data_source":"AXON RMS","district":"CP1","event_number":"CPD260420001269","field_subject_cid":"PEDESTRIAN","instance_id":"36768345-3701-415f-aec4-a39efeb9c06a","interview_date":"2026-04-20T19:48:00.000","is_juvenile":false,"latitude_x":"39.1097","location_type":"STREET_ADDRESS","location_x":"13XX Main St Cincinnati, OH","longitude_x":"-84.5124","officer_assignment":"D_1_VCS","priority":"122","race":"BLACK_OR_AFRICAN_AMERICAN","sex":"MALE","sna_neighborhood":"Over-the-Rhine"},
    {"action_taken_cid":"WARNING","age_range_cid":"36-45","data_source":"AXON RMS","district":"CP3","event_number":"CPD260420001049","field_subject_cid":"PEDESTRIAN","instance_id":"63819b7a-c51b-482a-a400-1db5f0784efa","interview_date":"2026-04-20T18:13:00.000","is_juvenile":false,"latitude_x":"39.1153","location_type":"STREET_ADDRESS","location_x":"10XX Woodlawn Ave Cincinnati, OH","longitude_x":"-84.5669","officer_assignment":"PV","priority":"125","race":"BLACK_OR_AFRICAN_AMERICAN","sex":"MALE","sna_neighborhood":"East Price Hill"},
    {"action_taken_cid":"WARNING","age_range_cid":"36-45","data_source":"AXON RMS","district":"CP3","event_number":"CPD260420001049","field_subject_cid":"PEDESTRIAN","instance_id":"63819b7a-c51b-482a-a400-1db5f0784efa","interview_date":"2026-04-20T18:13:00.000","is_juvenile":false,"latitude_x":"39.1062","location_type":"STREET_ADDRESS","location_x":"10XX Woodlawn Ave Cincinnati, OH","longitude_x":"-84.5674","officer_assignment":"PV","priority":"125","race":"BLACK_OR_AFRICAN_AMERICAN","sex":"MALE","sna_neighborhood":"East Price Hill"},
    {"action_taken_cid":"ARREST_FELONY","age_range_cid":"18-25","data_source":"AXON RMS","district":"CP3","event_number":"CPD260420001049","field_subject_cid":"PEDESTRIAN","instance_id":"63819b7a-c51b-482a-a400-1db5f0784efa","interview_date":"2026-04-20T18:13:00.000","is_juvenile":false,"latitude_x":"39.1087","location_type":"STREET_ADDRESS","location_x":"10XX Woodlawn Ave Cincinnati, OH","longitude_x":"-84.5665","officer_assignment":"PV","priority":"125","race":"BLACK_OR_AFRICAN_AMERICAN","sex":"MALE","sna_neighborhood":"East Price Hill"},
    {"action_taken_cid":"ARREST_MISD","age_range_cid":"46+","data_source":"AXON RMS","district":"CP3","event_number":"CPD260420001049","field_subject_cid":"PEDESTRIAN","instance_id":"63819b7a-c51b-482a-a400-1db5f0784efa","interview_date":"2026-04-20T18:13:00.000","is_juvenile":false,"latitude_x":"39.1066","location_type":"STREET_ADDRESS","location_x":"10XX Woodlawn Ave Cincinnati, OH","longitude_x":"-84.566","officer_assignment":"PV","priority":"125","race":"WHITE","sex":"FEMALE","sna_neighborhood":"East Price Hill"},
    {"action_taken_cid":"WARNING","age_range_cid":"26-35","data_source":"AXON RMS","district":"CP1","event_number":"CPD260420000925","field_subject_cid":"PEDESTRIAN","instance_id":"95376e3d-c96c-4fc4-9daa-81cb8a3b4078","interview_date":"2026-04-20T17:10:00.000","is_juvenile":false,"latitude_x":"39.1095","location_type":"STREET_ADDRESS","location_x":"7XX Central Ave Cincinnati, OH","longitude_x":"-84.5195","officer_assignment":"PV","priority":"122","race":"BLACK_OR_AFRICAN_AMERICAN","sex":"MALE","sna_neighborhood":"West End"},
    {"action_taken_cid":"NONE","age_range_cid":"46+","data_source":"AXON RMS","district":"CP4","event_number":"CPD260420000646","field_subject_cid":"PEDESTRIAN","instance_id":"0db1b1d9-8bb3-47b3-a2ee-8f322e902559","interview_date":"2026-04-20T15:44:00.000","is_juvenile":false,"latitude_x":"39.1648","location_type":"STREET_ADDRESS","location_x":"45XX Reading Rd Cincinnati, OH","longitude_x":"-84.47","officer_assignment":"D_4_F","priority":"123","race":"WHITE","sex":"MALE","sna_neighborhood":"Paddock Hills"},
    {"action_taken_cid":"WARNING","age_range_cid":"46+","data_source":"AXON RMS","district":"CP1","event_number":"CPD260420000503","field_subject_cid":"PEDESTRIAN","instance_id":"03d768d6-d1fa-4360-9c9e-44f5cba0dfd9","interview_date":"2026-04-20T14:03:00.000","is_juvenile":false,"latitude_x":"39.1049","location_type":"STREET_ADDRESS","location_x":"XX E Liberty St Cincinnati, OH","longitude_x":"-84.5152","officer_assignment":"D_1_F","priority":"125","race":"BLACK_OR_AFRICAN_AMERICAN","sex":"MALE","sna_neighborhood":"Over-the-Rhine"},
    {"action_taken_cid":"NONE","age_range_cid":"18-25","data_source":"AXON RMS","district":"CP2","event_number":"CPD260420000507","field_subject_cid":"PEDESTRIAN","instance_id":"a0560595-8e58-4dc1-8ef6-fddd756c1640","interview_date":"2026-04-20T13:55:00.000","is_juvenile":false,"latitude_x":"39.1596","location_type":"STREET_ADDRESS","location_x":"46XX Marburg Ave Cincinnati, OH","longitude_x":"-84.4272","officer_assignment":"D_2_F","priority":"124","race":"BLACK_OR_AFRICAN_AMERICAN","sex":"MALE","sna_neighborhood":"Oakley"},
    {"action_taken_cid":"NONE","age_range_cid":"0-17","data_source":"AXON RMS","district":"CP2","event_number":"CPD260420000507","field_subject_cid":"PEDESTRIAN","instance_id":"a0560595-8e58-4dc1-8ef6-fddd756c1640","interview_date":"2026-04-20T13:55:00.000","is_juvenile":true,"latitude_x":"39.1574","location_type":"STREET_ADDRESS","location_x":"46XX Marburg Ave Cincinnati, OH","longitude_x":"-84.4275","officer_assignment":"D_2_F","priority":"124","race":"BLACK_OR_AFRICAN_AMERICAN","sex":"MALE","sna_neighborhood":"Oakley"},
    {"action_taken_cid":"NONE","age_range_cid":"0-17","data_source":"AXON RMS","district":"CP2","event_number":"CPD260420000507","field_subject_cid":"PEDESTRIAN","instance_id":"a0560595-8e58-4dc1-8ef6-fddd756c1640","interview_date":"2026-04-20T13:55:00.000","is_juvenile":true,"latitude_x":"39.1517","location_type":"STREET_ADDRESS","location_x":"46XX Marburg Ave Cincinnati, OH","longitude_x":"-84.4269","officer_assignment":"D_2_F","priority":"124","race":"BLACK_OR_AFRICAN_AMERICAN","sex":"FEMALE","sna_neighborhood":"Oakley"}
  ]
}
